{
  "students": [
    {
      "absences": [],
      "can_signin": false,
      "deleted": false,
      "can_signout": true,
      "in_class": false,
      "authorized": [
        "vishesh"
      ],
      "id": 123513,
      "name": "bob"
    },
    {
      "absences": ["2015-07-11"],
      "can_signin": false,
      "deleted": false,
      "can_signout": true,
      "in_class": false,
      "authorized": [
        "vishesh"
      ],
      "id": 123512,
      "name": "george"
    }
  ],
  "users": [
    {
      "deleted": false,
      "id": 1239123981,
      "name": "phillip",
      "permissions": []
    },
    {
      "deleted": false,
      "id": 123912930123,
      "name": "vishesh",
      "permissions": []
    }
  ],
  "interactions": [
    {
      "date": "2015-07-11",
      "time_in": "08:00:23",
      "time_out": "17:03:41",
      "student": "bob"
    },
    {
      "date": "2015-07-12",
      "time_in": "08:00:23",
      "time_out": "17:03:41",
      "student": "bob"
    },
    {
      "date": "2015-07-12",
      "time_in": "08:00:23",
      "time_out": "17:03:41",
      "student": "george"
    }
  ]
}
